portfolyo/__init__.py
portfolyo/__version__.py
portfolyo/core/__init__.py
portfolyo/core/commodity/commodity.py
portfolyo/core/extendpandas.py
portfolyo/core/pfline/__init__.py
portfolyo/core/pfline/arithmatic.py
portfolyo/core/pfline/children.py
portfolyo/core/pfline/classes.py
portfolyo/core/pfline/create.py
portfolyo/core/pfline/dataframeexport.py
portfolyo/core/pfline/decorators.py
portfolyo/core/pfline/developernotes.py
portfolyo/core/pfline/enums.py
portfolyo/core/pfline/flat_helper.py
portfolyo/core/pfline/flat_methods.py
portfolyo/core/pfline/interop.py
portfolyo/core/pfline/nested_helper.py
portfolyo/core/pfline/nested_methods.py
portfolyo/core/pfline/plot.py
portfolyo/core/pfline/text.py
portfolyo/core/pfstate/__init__.py
portfolyo/core/pfstate/arithmatic.py
portfolyo/core/pfstate/pfstate.py
portfolyo/core/pfstate/pfstate_helper.py
portfolyo/core/pfstate/plot.py
portfolyo/core/pfstate/text.py
portfolyo/core/shared/__init__.py
portfolyo/core/shared/excelclipboard.py
portfolyo/core/shared/ndframelike.py
portfolyo/core/shared/text.py
portfolyo/core/suppresswarnings.py
portfolyo/dev/__init__.py
portfolyo/dev/develop.py
portfolyo/dev/mockup.py
portfolyo/todo.txt
portfolyo/tools/__init__.py
portfolyo/tools/ceil.py
portfolyo/tools/changefreq.py
portfolyo/tools/characterize.py
portfolyo/tools/duration.py
portfolyo/tools/floor.py
portfolyo/tools/frame.py
portfolyo/tools/freq.py
portfolyo/tools/hedge.py
portfolyo/tools/intersect.py
portfolyo/tools/isboundary.py
portfolyo/tools/leftandright.py
portfolyo/tools/peakconvert.py
portfolyo/tools/peakfn.py
portfolyo/tools/product.py
portfolyo/tools/right.py
portfolyo/tools/righttoleft.py
portfolyo/tools/round.py
portfolyo/tools/stamp.py
portfolyo/tools/standardize.py
portfolyo/tools/startofday.py
portfolyo/tools/testing.py
portfolyo/tools/trim.py
portfolyo/tools/types.py
portfolyo/tools/tzone.py
portfolyo/tools/unit.py
portfolyo/tools/unitdefinitions.txt
portfolyo/tools/visualize/__init__.py
portfolyo-0.6.7.dist-info/LICENCE
portfolyo-0.6.7.dist-info/METADATA
portfolyo-0.6.7.dist-info/WHEEL
portfolyo-0.6.7.dist-info/RECORD
