Metadata-Version: 2.3
Name: portfolyo
Version: 0.6.7
Summary: Analyse and manipulate timeseries related to power and gas offtake portfolios
License: BSD-3
Author: Ruud Wijtvliet
Author-email: rwijtvliet@gmail.com
Requires-Python: >=3.10,<4.0
Classifier: License :: Other/Proprietary License
Classifier: Programming Language :: Python :: 3
Classifier: Programming Language :: Python :: 3.10
Classifier: Programming Language :: Python :: 3.11
Classifier: Programming Language :: Python :: 3.12
Classifier: Programming Language :: Python :: 3.13
Requires-Dist: colorama (>=0.4.6,<0.5.0)
Requires-Dist: matplotlib (>=3.7.2,<4.0.0)
Requires-Dist: numpy (>=1.26.2,<2.0.0)
Requires-Dist: pandas (>=2.2,<3.0)
Requires-Dist: pint (>=0.24,<0.25)
Requires-Dist: pint-pandas (==0.6)
